cathalla/__init__.py
cathalla-0.0.5.dist-info/LICENSE
cathalla-0.0.5.dist-info/METADATA
cathalla-0.0.5.dist-info/WHEEL
cathalla-0.0.5.dist-info/RECORD
