Metadata-Version: 2.1
Name: cathalla
Version: 0.0.5
Summary: The Valhalla of Python
Home-page: https://impalah.github.io/cathalla/
License: MIT
Keywords: valhalla,python
Author: impalah
Author-email: impalah@gmail.com
Requires-Python: >=3.10
Classifier: Development Status :: 4 - Beta
Classifier: Intended Audience :: Developers
Classifier: License :: OSI Approved :: MIT License
Classifier: Programming Language :: Python :: 3
Classifier: Programming Language :: Python :: 3.10
Classifier: Programming Language :: Python :: 3.11
Classifier: Programming Language :: Python :: 3.12
Classifier: Topic :: Software Development :: Libraries :: Python Modules
Project-URL: Documentation, https://impalah.github.io/cathalla/
Project-URL: Repository, https://github.com/impalah/cathalla
Project-URL: Source, https://github.com/impalah/cathalla
